black_codeclimate/__init__.py
black_codeclimate/__main__.py
black_codeclimate/generate_report.py
black_codeclimate-1.0.3.dist-info/LICENSE
black_codeclimate-1.0.3.dist-info/METADATA
black_codeclimate-1.0.3.dist-info/WHEEL
black_codeclimate-1.0.3.dist-info/entry_points.txt
black_codeclimate-1.0.3.dist-info/RECORD
