Metadata-Version: 2.1
Name: black-codeclimate
Version: 1.0.3
Summary: Convert black --diff output to a Code Climate report
Home-page: https://github.com/steinuil/black-codeclimate
License: MIT
Keywords: Black,CodeClimate,GitLab,GitLab-CI,Code Quality
Author: steinuil
Author-email: steenuil.owl@gmail.com
Requires-Python: >=3.8,<4.0
Classifier: License :: OSI Approved :: MIT License
Classifier: Programming Language :: Python :: 3
Classifier: Programming Language :: Python :: 3.8
Classifier: Programming Language :: Python :: 3.9
Classifier: Programming Language :: Python :: 3.10
Classifier: Programming Language :: Python :: 3.11
Classifier: Programming Language :: Python :: 3.12
Requires-Dist: unidiff (>=0.7.5,<0.8.0)
Project-URL: Repository, https://github.com/steinuil/black-codeclimate
